html2rl/__init__.py
html2rl/rlconversions.py
html2rl-0.0.1.dist-info/LICENSE
html2rl-0.0.1.dist-info/METADATA
html2rl-0.0.1.dist-info/WHEEL
html2rl-0.0.1.dist-info/top_level.txt
html2rl-0.0.1.dist-info/RECORD
